{
	"format_version": "1.8.0",
	"animations": {
		"animation.orc.walk": {
			"loop": true,
			"animation_length": 2,
			"bones": {
				"bipedLeftArm": {
					"rotation": {
						"0.0": {
							"vector": [0, 0, 0]
						},
						"0.25": {
							"vector": [20, 0, 0],
							"easing": "linear"
						},
						"0.5": {
							"vector": [40, 0, 0],
							"easing": "easeOutSine"
						},
						"0.75": {
							"vector": [20, 0, 0],
							"easing": "easeInSine"
						},
						"1.0": {
							"vector": [0, 0, 0],
							"easing": "linear"
						},
						"1.25": {
							"vector": [-20, 0, 0],
							"easing": "linear"
						},
						"1.5": {
							"vector": [-33, 0, 0],
							"easing": "easeOutSine"
						},
						"1.75": {
							"vector": [-19, 0, 0],
							"easing": "easeInSine"
						},
						"2.0": {
							"vector": [0, 0, 0],
							"easing": "linear"
						}
					}
				},
				"bipedShield": {
					"relative_to": {
						"rotation": "entity"
					},
					"rotation": {
						"0.0": {
							"vector": [0, 0, 0]
						},
						"0.25": {
							"vector": [20, 0, 0],
							"easing": "linear"
						},
						"0.5": {
							"vector": [40, 0, 0],
							"easing": "easeOutSine"
						},
						"0.75": {
							"vector": [20, 0, 0],
							"easing": "easeInSine"
						},
						"1.0": {
							"vector": [0, 0, 0],
							"easing": "linear"
						},
						"1.25": {
							"vector": [-20, 0, 0],
							"easing": "linear"
						},
						"1.5": {
							"vector": [-33, 0, 0],
							"easing": "easeOutSine"
						},
						"1.75": {
							"vector": [-19, 0, 0],
							"easing": "easeInSine"
						},
						"2.0": {
							"vector": [0, 0, 0],
							"easing": "linear"
						}
					}
				},
				"bipedLeftShoulder": {
					"relative_to": {
						"rotation": "entity"
					},
					"rotation": {
						"0.0": {
							"vector": [0, 0, 0]
						},
						"0.25": {
							"vector": [20, 0, 0],
							"easing": "linear"
						},
						"0.5": {
							"vector": [40, 0, 0],
							"easing": "easeOutSine"
						},
						"0.75": {
							"vector": [20, 0, 0],
							"easing": "easeInSine"
						},
						"1.0": {
							"vector": [0, 0, 0],
							"easing": "linear"
						},
						"1.25": {
							"vector": [-20, 0, 0],
							"easing": "linear"
						},
						"1.5": {
							"vector": [-33, 0, 0],
							"easing": "easeOutSine"
						},
						"1.75": {
							"vector": [-19, 0, 0],
							"easing": "easeInSine"
						},
						"2.0": {
							"vector": [0, 0, 0],
							"easing": "linear"
						}
					}
				},
				"bipedRightArm": {
					"rotation": {
						"0.0": {
							"vector": [0, 0, 0]
						},
						"0.25": {
							"vector": [20, 0, 0],
							"easing": "linear"
						},
						"0.5": {
							"vector": [40, 0, 0],
							"easing": "easeOutSine"
						},
						"0.75": {
							"vector": [20, 0, 0],
							"easing": "easeInSine"
						},
						"1.0": {
							"vector": [0, 0, 0],
							"easing": "linear"
						},
						"1.25": {
							"vector": [-20, 0, 0],
							"easing": "linear"
						},
						"1.5": {
							"vector": [-33, 0, 0],
							"easing": "easeOutSine"
						},
						"1.75": {
							"vector": [-19, 0, 0],
							"easing": "easeInSine"
						},
						"2.0": {
							"vector": [0, 0, 0],
							"easing": "linear"
						}
					}
				},
				"heldItemRight": {
					"rotation": {
						"0.0": {
							"vector": [0, 0, 0]
						},
						"0.25": {
							"vector": [20, 0, 0],
							"easing": "linear"
						},
						"0.5": {
							"vector": [40, 0, 0],
							"easing": "easeOutSine"
						},
						"0.75": {
							"vector": [20, 0, 0],
							"easing": "easeInSine"
						},
						"0.8333": {
							"vector": [14.05, 0, 0]
						},
						"1.0": {
							"vector": [0, 0, 0],
							"easing": "linear"
						},
						"1.25": {
							"vector": [-20, 0, 0],
							"easing": "linear"
						},
						"1.5": {
							"vector": [-33, 0, 0],
							"easing": "easeOutSine"
						},
						"1.75": {
							"vector": [-19, 0, 0],
							"easing": "easeInSine"
						},
						"2.0": {
							"vector": [0, 0, 0],
							"easing": "linear"
						}
					}
				},
				"bipedRightShoulder": {
					"rotation": {
						"0.0": {
							"vector": [0, 0, 0]
						},
						"0.25": {
							"vector": [20, 0, 0],
							"easing": "linear"
						},
						"0.5": {
							"vector": [40, 0, 0],
							"easing": "easeOutSine"
						},
						"0.75": {
							"vector": [20, 0, 0],
							"easing": "easeInSine"
						},
						"1.0": {
							"vector": [0, 0, 0],
							"easing": "linear"
						},
						"1.25": {
							"vector": [-20, 0, 0],
							"easing": "linear"
						},
						"1.5": {
							"vector": [-33, 0, 0],
							"easing": "easeOutSine"
						},
						"1.75": {
							"vector": [-19, 0, 0],
							"easing": "easeInSine"
						},
						"2.0": {
							"vector": [0, 0, 0],
							"easing": "linear"
						}
					}
				},
				"bipedLeftLeg": {
					"rotation": {
						"0.0": {
							"vector": [20, 0, 0],
							"easing": "linear"
						},
						"0.25": {
							"vector": [40, 0, 0],
							"easing": "easeOutSine"
						},
						"0.5": {
							"vector": [20, 0, 0],
							"easing": "easeInSine"
						},
						"0.75": {
							"vector": [0, 0, 0],
							"easing": "linear"
						},
						"1.0": {
							"vector": [-20, 0, 0],
							"easing": "linear"
						},
						"1.25": {
							"vector": [-33, 0, 0],
							"easing": "easeOutSine"
						},
						"1.5": {
							"vector": [-19, 0, 0],
							"easing": "easeInSine"
						},
						"1.75": {
							"vector": [0, 0, 0],
							"easing": "linear"
						},
						"2.0": {
							"vector": [20, 0, 0],
							"easing": "linear"
						}
					}
				},
				"bipedRightLeg": {
					"rotation": {
						"0.0": {
							"vector": [-20, 0, 0],
							"easing": "linear"
						},
						"0.25": {
							"vector": [-40, 0, 0],
							"easing": "easeOutSine"
						},
						"0.5": {
							"vector": [-20, 0, 0],
							"easing": "easeInSine"
						},
						"0.75": {
							"vector": [0, 0, 0]
						},
						"1.0": {
							"vector": [20, 0, 0],
							"easing": "linear"
						},
						"1.25": {
							"vector": [40, 0, 0],
							"easing": "easeOutSine"
						},
						"1.5": {
							"vector": [20, 0, 0],
							"easing": "easeInSine"
						},
						"1.75": {
							"vector": [0, 0, 0]
						},
						"2.0": {
							"vector": [-20, 0, 0],
							"easing": "linear"
						}
					}
				}
			}
		},
		"animation.orc.attack": {
			"animation_length": 1,
			"override_previous_animation": true,
			"bones": {
				"bipedRightArm": {
					"rotation": {
						"0.0": {
							"vector": [0, 0, 0]
						},
						"0.625": {
							"vector": [124, 0, 0]
						},
						"1.0": {
							"vector": [0, 0, 0]
						}
					}
				},
				"heldItemRight": {
					"rotation": {
						"0.0": {
							"vector": [0, 0, 0]
						},
						"0.2083": {
							"vector": [124, 0, 0]
						},
						"0.625": {
							"vector": [0, 0, 0]
						}
					}
				},
				"bipedRightShoulder": {
					"rotation": {
						"0.0": {
							"vector": [0, 0, 0]
						},
						"0.625": {
							"vector": [124, 0, 0]
						},
						"1.0": {
							"vector": [0, 0, 0]
						}
					}
				}
			}
		},
		"animation.orc.spawn": {
			"loop": "hold_on_last_frame",
			"animation_length": 0.5,
			"bones": {
				"bipedHead": {
					"scale": {
						"0.0": {
							"vector": [0, 0, 0]
						},
						"0.5": {
							"vector": [1, 1, 1]
						}
					}
				},
				"bipedHeadwear": {
					"scale": {
						"0.0": {
							"vector": [0, 0, 0]
						},
						"0.5": {
							"vector": [1, 1, 1]
						}
					}
				},
				"bipedHeadwear1": {
					"scale": {
						"0.0": {
							"vector": [0, 0, 0]
						},
						"0.5": {
							"vector": [1, 1, 1]
						}
					}
				},
				"bipedHeadwear2": {
					"scale": {
						"0.0": {
							"vector": [0, 0, 0]
						},
						"0.5": {
							"vector": [1, 1, 1]
						}
					}
				},
				"bipedHeadwear3": {
					"scale": {
						"0.0": {
							"vector": [0, 0, 0]
						},
						"0.5": {
							"vector": [1, 1, 1]
						}
					}
				},
				"bipedBodytop": {
					"scale": {
						"0.0": {
							"vector": [0, 0, 0]
						},
						"0.5": {
							"vector": [1, 1, 1]
						}
					}
				},
				"bipedBodybot": {
					"scale": {
						"0.0": {
							"vector": [0, 0, 0]
						},
						"0.5": {
							"vector": [1, 1, 1]
						}
					}
				},
				"bipedLeftArm": {
					"scale": {
						"0.0": {
							"vector": [0, 0, 0]
						},
						"0.5": {
							"vector": [1, 1, 1]
						}
					}
				},
				"bipedShield": {
					"scale": {
						"0.0": {
							"vector": [0, 0, 0]
						},
						"0.5": {
							"vector": [1, 1, 1]
						}
					}
				},
				"bipedLeftShoulder": {
					"scale": {
						"0.0": {
							"vector": [0, 0, 0]
						},
						"0.5": {
							"vector": [1, 1, 1]
						}
					}
				},
				"bipedRightArm": {
					"scale": {
						"0.0": {
							"vector": [0, 0, 0]
						},
						"0.5": {
							"vector": [1, 1, 1]
						}
					}
				},
				"heldItemRight": {
					"scale": {
						"0.0": {
							"vector": [0, 0, 0]
						},
						"0.5": {
							"vector": [1, 1, 1]
						}
					}
				},
				"bipedRightShoulder": {
					"rotation": {
						"vector": [-20, 0, 0],
						"easing": "linear"
					},
					"scale": {
						"0.0": {
							"vector": [0, 0, 0]
						},
						"0.5": {
							"vector": [1, 1, 1]
						}
					}
				},
				"bipedLeftLeg": {
					"scale": {
						"0.0": {
							"vector": [0, 0, 0]
						},
						"0.5": {
							"vector": [1, 1, 1]
						}
					}
				},
				"bipedRightLeg": {
					"scale": {
						"0.0": {
							"vector": [0, 0, 0]
						},
						"0.5": {
							"vector": [1, 1, 1]
						}
					}
				}
			},
			"particle_effects": {}
		},
		"animation.orc.idle": {
			"loop": true,
			"animation_length": 2,
			"bones": {
				"bipedHead": {
					"rotation": {
						"0.0": {
							"vector": [0, 0, 0]
						},
						"0.5": {
							"vector": [0, 15, 0]
						},
						"1.0417": {
							"vector": [0, 0, 0]
						},
						"1.5": {
							"vector": [0, -15, 0]
						},
						"2.0": {
							"vector": [0, 0, 0]
						}
					}
				},
				"bipedHeadwear": {
					"rotation": {
						"0.0": {
							"vector": [0, 0, 0]
						},
						"0.5": {
							"vector": [0, 15, 0]
						},
						"1.0417": {
							"vector": [0, 0, 0]
						},
						"1.5": {
							"vector": [0, -15, 0]
						},
						"2.0": {
							"vector": [0, 0, 0]
						}
					}
				},
				"bipedHeadwear1": {
					"rotation": {
						"0.0": {
							"vector": [0, 0, 0]
						},
						"0.5": {
							"vector": [0, 15, 0]
						},
						"1.0417": {
							"vector": [0, 0, 0]
						},
						"1.5": {
							"vector": [0, -15, 0]
						},
						"2.0": {
							"vector": [0, 0, 0]
						}
					}
				},
				"bipedHeadwear2": {
					"rotation": {
						"0.0": {
							"vector": [0, 0, 0]
						},
						"0.5": {
							"vector": [0, 15, 0]
						},
						"1.0417": {
							"vector": [0, 0, 0]
						},
						"1.5": {
							"vector": [0, -15, 0]
						},
						"2.0": {
							"vector": [0, 0, 0]
						}
					}
				},
				"bipedHeadwear3": {
					"rotation": {
						"0.0": {
							"vector": [0, 0, 0]
						},
						"0.5": {
							"vector": [0, 15, 0]
						},
						"1.0417": {
							"vector": [0, 0, 0]
						},
						"1.5": {
							"vector": [0, -15, 0]
						},
						"2.0": {
							"vector": [0, 0, 0]
						}
					}
				}
			}
		}
	}
}